tiktok_rapidapi/__init__.py
tiktok_rapidapi/api.py
tiktok_rapidapi/schemas/__init__.py
tiktok_rapidapi/schemas/base.py
tiktok_rapidapi/schemas/comment.py
tiktok_rapidapi/schemas/content.py
tiktok_rapidapi/schemas/user.py
tiktok_rapidapi/schemas/video.py
tiktok_rapidapi-0.2.2.dist-info/LICENSE
tiktok_rapidapi-0.2.2.dist-info/METADATA
tiktok_rapidapi-0.2.2.dist-info/WHEEL
tiktok_rapidapi-0.2.2.dist-info/top_level.txt
tiktok_rapidapi-0.2.2.dist-info/RECORD
