Metadata-Version: 2.1
Name: tiktok_rapidapi
Version: 0.2.2
Summary: TikTok API on RapidAPI
Home-page: https://github.com/dankaprogg/tiktok_rapidapi
Author: Daniil Shvedov
Author-email: dshvedov@kotspin.ru
Keywords: rapidapi,tiktok,parsing
License-File: LICENSE
